loops_diff/__init__.py
loops_diff/_version.py
loops_diff-1.1.1.data/data/share/jupyter/labextensions/loops-diff/package.json
loops_diff-1.1.1.data/data/share/jupyter/labextensions/loops-diff/schemas/loops-diff/package.json.orig
loops_diff-1.1.1.data/data/share/jupyter/labextensions/loops-diff/schemas/loops-diff/plugin.json
loops_diff-1.1.1.data/data/share/jupyter/labextensions/loops-diff/static/1065.fd670f9fb5606734100a.js
loops_diff-1.1.1.data/data/share/jupyter/labextensions/loops-diff/static/1065.fd670f9fb5606734100a.js.LICENSE.txt
loops_diff-1.1.1.data/data/share/jupyter/labextensions/loops-diff/static/1134.d14ebdf244e4025499a2.js
loops_diff-1.1.1.data/data/share/jupyter/labextensions/loops-diff/static/1134.d14ebdf244e4025499a2.js.LICENSE.txt
loops_diff-1.1.1.data/data/share/jupyter/labextensions/loops-diff/static/1147.8b4293592a35884c7541.js
loops_diff-1.1.1.data/data/share/jupyter/labextensions/loops-diff/static/1147.8b4293592a35884c7541.js.LICENSE.txt
loops_diff-1.1.1.data/data/share/jupyter/labextensions/loops-diff/static/1156.00a9b47e808c92d61873.js
loops_diff-1.1.1.data/data/share/jupyter/labextensions/loops-diff/static/1156.00a9b47e808c92d61873.js.LICENSE.txt
loops_diff-1.1.1.data/data/share/jupyter/labextensions/loops-diff/static/1259.2e9b1595188d0ec24e1f.js
loops_diff-1.1.1.data/data/share/jupyter/labextensions/loops-diff/static/1259.2e9b1595188d0ec24e1f.js.LICENSE.txt
loops_diff-1.1.1.data/data/share/jupyter/labextensions/loops-diff/static/1420.2b3e2cd467a49a01741b.js
loops_diff-1.1.1.data/data/share/jupyter/labextensions/loops-diff/static/1420.2b3e2cd467a49a01741b.js.LICENSE.txt
loops_diff-1.1.1.data/data/share/jupyter/labextensions/loops-diff/static/1448.e6798bc4c005bde83007.js
loops_diff-1.1.1.data/data/share/jupyter/labextensions/loops-diff/static/1448.e6798bc4c005bde83007.js.LICENSE.txt
loops_diff-1.1.1.data/data/share/jupyter/labextensions/loops-diff/static/147.d5b41801595cbd1cf764.js
loops_diff-1.1.1.dist-info/METADATA
loops_diff-1.1.1.dist-info/WHEEL
loops_diff-1.1.1.dist-info/licenses/LICENSE
loops_diff-1.1.1.dist-info/RECORD
