Metadata-Version: 2.3
Name: loops_diff
Version: 1.1.1
Dynamic: Keywords
Summary: A JupyterLab extension to support iterative and exploratory data analysis in computational notebooks.
Project-URL: Homepage, https://github.com/jku-vds-lab/loops
Project-URL: Bug Tracker, https://github.com/jku-vds-lab/loops/issues
Project-URL: Repository, https://github.com/jku-vds-lab/loops.git
Author-email: Klaus Eckelt <klaus@eckelt.info>
License: BSD 3-Clause License
License-File: LICENSE
Classifier: Framework :: Jupyter
Classifier: Framework :: Jupyter :: JupyterLab
Classifier: Framework :: Jupyter :: JupyterLab :: 4
Classifier: Framework :: Jupyter :: JupyterLab :: Extensions
Classifier: Framework :: Jupyter :: JupyterLab :: Extensions :: Prebuilt
Classifier: License :: OSI Approved :: BSD License
Classifier: Programming Language :: Python
Classifier: Programming Language :: Python :: 3
Classifier: Programming Language :: Python :: 3.8
Classifier: Programming Language :: Python :: 3.9
Classifier: Programming Language :: Python :: 3.10
Classifier: Programming Language :: Python :: 3.11
Classifier: Programming Language :: Python :: 3.12
Requires-Python: >=3.8
